plantdb/server/__init__.py
plantdb/server/rest_api.py
plantdb/server/test_rest_api.py
plantdb/server/webcache.py
plantdb/server/cli/__init__.py
plantdb/server/cli/fsdb_rest_api.py
plantdb/server/cli/wsgi.py
plantdb_server-0.14.5.dist-info/METADATA
plantdb_server-0.14.5.dist-info/WHEEL
plantdb_server-0.14.5.dist-info/entry_points.txt
plantdb_server-0.14.5.dist-info/top_level.txt
plantdb_server-0.14.5.dist-info/RECORD
