Metadata-Version: 2.4
Name: plantdb.server
Version: 0.14.5
Summary: Server-side component of the ROMI plant database system.
Author-email: Peter Hanappe <peter.hanappe@sony.com>, Timothée Wintz <timothee@timwin.fr>, Nabil Ait Taleb <mohamednabil.aittaleb@sony.com>, Arthur Luciani <arthur.luciani@ens-lyon.fr>
Maintainer-email: Jonathan Legrand <jonathan.legrand@ens-lyon.fr>
License: LGPL-3.0-or-later
Project-URL: homepage, https://romi-project.eu/
Project-URL: documentation, https://docs.romi-project.eu/plant_imager/
Project-URL: source, https://github.com/romi/plantdb
Project-URL: issues, https://github.com/romi/plantdb/issues
Keywords: Robotics for Microfarms,ROMI,Plant Phenotyping,Scientific Database,Data Management,REST API
Classifier: Programming Language :: Python :: 3
Classifier: Development Status :: 4 - Beta
Classifier: Intended Audience :: Science/Research
Classifier: Topic :: Database
Classifier: Topic :: Scientific/Engineering :: Bio-Informatics
Classifier: Topic :: Software Development :: Libraries :: Python Modules
Classifier: Topic :: Internet :: WWW/HTTP :: WSGI :: Server
Classifier: Topic :: System :: Networking
Classifier: Framework :: Flask
Classifier: Operating System :: OS Independent
Classifier: Natural Language :: English
Requires-Python: >=3.8
Requires-Dist: plantdb.commons
Requires-Dist: bcrypt
Requires-Dist: flask
Requires-Dist: flask-cors
Requires-Dist: flask-restful
Requires-Dist: requests
Requires-Dist: toml
Provides-Extra: doc
Requires-Dist: mkdocs; extra == "doc"
Requires-Dist: mkdocs-material; extra == "doc"
Requires-Dist: mkdocstrings[python]; extra == "doc"
Requires-Dist: pymdown-extensions; extra == "doc"
Requires-Dist: markdown-exec[ansi]; extra == "doc"
Requires-Dist: mkdocs-gen-files; extra == "doc"
Requires-Dist: mkdocs-literate-nav; extra == "doc"
Requires-Dist: mkdocs-section-index; extra == "doc"
Provides-Extra: test
Requires-Dist: nose2[coverage]; extra == "test"
Requires-Dist: coverage[toml]; extra == "test"
Requires-Dist: networkx; extra == "test"
Requires-Dist: tifffile; extra == "test"
